README.md
setup.py
s3_tar/__init__.py
s3_tar/cli.py
s3_tar/s3_mpu.py
s3_tar/s3_tar.py
s3_tar/utils.py
s3_tar.egg-info/PKG-INFO
s3_tar.egg-info/SOURCES.txt
s3_tar.egg-info/dependency_links.txt
s3_tar.egg-info/entry_points.txt
s3_tar.egg-info/requires.txt
s3_tar.egg-info/top_level.txt