Metadata-Version: 2.1
Name: s3-tar
Version: 0.1.13
Summary: Tar (and compress) files in s3
Home-page: https://github.com/xtream1101/s3-tar
Author: Eddy Hintze
Author-email: eddy@hintze.co
License: MIT
Platform: UNKNOWN
Classifier: Programming Language :: Python :: 3
Classifier: Operating System :: OS Independent
Classifier: Topic :: Software Development :: Libraries :: Python Modules
Classifier: Topic :: Utilities
